ProtFlash/__init__.py
ProtFlash/model.py
ProtFlash/pretrain.py
ProtFlash/utils.py
ProtFlash-0.1.1.dist-info/LICENSE
ProtFlash-0.1.1.dist-info/METADATA
ProtFlash-0.1.1.dist-info/WHEEL
ProtFlash-0.1.1.dist-info/top_level.txt
ProtFlash-0.1.1.dist-info/RECORD
