Metadata-Version: 2.1
Name: ProtFlash
Version: 0.1.1
Summary: protein language model
Home-page: http://github.com/isyslab-hust/ProtFlash
Author: Lei Wang
Author-email: wanglei94@hust.edu.cn
License: MIT
Keywords: protein language model
Classifier: Development Status :: 3 - Alpha
Classifier: Intended Audience :: Developers
Classifier: License :: OSI Approved :: MIT License
Classifier: Programming Language :: Python :: 3
License-File: LICENSE
Requires-Dist: einops
Requires-Dist: torch
Requires-Dist: numpy
